Alt/Dashboard/AgentManager.py
Alt/Dashboard/__init__.py
Alt/Dashboard/dashboard.py
matrix_alt_dashboard-0.0.2.dist-info/licenses/LICENSE.txt
matrix_alt_dashboard-0.0.2.dist-info/METADATA
matrix_alt_dashboard-0.0.2.dist-info/WHEEL
matrix_alt_dashboard-0.0.2.dist-info/top_level.txt
matrix_alt_dashboard-0.0.2.dist-info/RECORD
