Metadata-Version: 2.4
Name: Matrix-Alt-Dashboard
Version: 0.0.2
Summary: Package contains code to run the agent dashboard for Alt Agentss
Home-page: https://github.com/Team488/Alt
Author: The Matrix 488
Author-email: 488matrix@gmail.com
Project-URL: Bug Tracker, https://github.com/Team488/Alt/issues
Project-URL: repository, https://github.com/Team488/Alt
Classifier: Programming Language :: Python :: 3
Classifier: License :: OSI Approved :: MIT License
Classifier: Operating System :: OS Independent
Requires-Python: >=3.9
License-File: LICENSE.txt
Requires-Dist: Matrix-Alt-Core==0.0.1
Requires-Dist: XTablesClient==5.7.9
Requires-Dist: Flask==3.1.0
Requires-Dist: Flask-SocketIO==5.5.1
Dynamic: license-file
